delta_rest_api_india/__init__.py
delta_rest_api_india/delta_rest_api_india.py
delta_rest_api_india-3.2.dist-info/licenses/LICENSE
delta_rest_api_india-3.2.dist-info/METADATA
delta_rest_api_india-3.2.dist-info/WHEEL
delta_rest_api_india-3.2.dist-info/top_level.txt
delta_rest_api_india-3.2.dist-info/RECORD
