Metadata-Version: 2.4
Name: delta_rest_api_india
Version: 3.2
Summary: DELTA ALOG 
Author: Shashank Joshi
Author-email: Shashank Joshi <shashankjoshi61@yahoo.com>
License: MIT
Keywords: delta,delta api,crypto algo,delta algo
Requires-Python: >=3.8
License-File: LICENSE
Requires-Dist: requests
Requires-Dist: ta
Requires-Dist: ccxt
Requires-Dist: pandas
Dynamic: license-file
